Metadata-Version: 2.1
Name: manufacturingpy
Version: 0.0.1
Summary: Calculating, formulas and concepts for industries
Author: Sergio Paiva de Campos
Author-email: sergiokmpos@gmail.com
License: MIT Licence
Keywords: manufacturing
